openvpn_status/__init__.py
openvpn_status/descriptors.py
openvpn_status/models.py
openvpn_status/parser.py
openvpn_status/shortcuts.py
openvpn_status/utils.py
openvpn_status-0.2.2.dist-info/AUTHORS.rst
openvpn_status-0.2.2.dist-info/LICENSE
openvpn_status-0.2.2.dist-info/METADATA
openvpn_status-0.2.2.dist-info/WHEEL
openvpn_status-0.2.2.dist-info/top_level.txt
openvpn_status-0.2.2.dist-info/RECORD
