Metadata-Version: 2.1
Name: openvpn-status
Version: 0.2.2
Summary: Parse OpenVPN status logs in Python
Home-page: https://github.com/tonyseek/openvpn-status
Author: Jiangge Zhang
Author-email: tonyseek@gmail.com
License: MIT
Keywords: openvpn,status,log
Platform: Any
Classifier: Development Status :: 3 - Alpha
Classifier: Intended Audience :: Developers
Classifier: Intended Audience :: System Administrators
Classifier: License :: OSI Approved :: MIT License
Classifier: Operating System :: OS Independent
Classifier: Programming Language :: Python :: 2
Classifier: Programming Language :: Python :: 2.7
Classifier: Programming Language :: Python :: 3
Classifier: Programming Language :: Python :: 3.6
Classifier: Programming Language :: Python :: 3.7
Classifier: Programming Language :: Python :: 3.8
Classifier: Programming Language :: Python :: 3.9
Classifier: Programming Language :: Python :: 3.10
Classifier: Programming Language :: Python :: Implementation :: CPython
Classifier: Programming Language :: Python :: Implementation :: PyPy
Classifier: Topic :: Internet :: Log Analysis
Classifier: Topic :: Software Development :: Libraries :: Python Modules
Classifier: Topic :: System :: Logging
Classifier: Topic :: Text Processing
Classifier: Topic :: Utilities
License-File: LICENSE
License-File: AUTHORS.rst
